napari_bluesky/__init__.py
napari_bluesky/_version.py
napari_bluesky/_widget.py
napari_bluesky/napari.yaml
napari_bluesky/_tests/__init__.py
napari_bluesky/_tests/test_widget.py
napari_bluesky-0.0.2.dist-info/LICENSE
napari_bluesky-0.0.2.dist-info/METADATA
napari_bluesky-0.0.2.dist-info/WHEEL
napari_bluesky-0.0.2.dist-info/entry_points.txt
napari_bluesky-0.0.2.dist-info/top_level.txt
napari_bluesky-0.0.2.dist-info/RECORD
