Metadata-Version: 2.1
Name: napari-bluesky
Version: 0.0.2
Summary: A plugin for posting to Bluesky from napari
Author: Kyle Harrington
Author-email: bluesky@kyleharrington.com
License: 
Project-URL: Bug Tracker, https://github.com/kephale/napari-bluesky/issues
Project-URL: Documentation, https://github.com/kephale/napari-bluesky#README.md
Project-URL: Source Code, https://github.com/kephale/napari-bluesky
Project-URL: User Support, https://github.com/kephale/napari-bluesky/issues
Classifier: Development Status :: 2 - Pre-Alpha
Classifier: Framework :: napari
Classifier: Intended Audience :: Developers
Classifier: License :: OSI Approved :: MIT License
Classifier: Operating System :: OS Independent
Classifier: Programming Language :: Python
Classifier: Programming Language :: Python :: 3
Classifier: Programming Language :: Python :: 3 :: Only
Classifier: Programming Language :: Python :: 3.9
Classifier: Programming Language :: Python :: 3.10
Classifier: Programming Language :: Python :: 3.11
Classifier: Programming Language :: Python :: 3.12
Classifier: Topic :: Scientific/Engineering :: Image Processing
Requires-Python: >=3.9
License-File: LICENSE
Requires-Dist: numpy
Requires-Dist: magicgui
Requires-Dist: qtpy
Requires-Dist: scikit-image
Requires-Dist: atproto
Requires-Dist: appdirs
Requires-Dist: python-dotenv
Requires-Dist: pillow
Provides-Extra: testing
Requires-Dist: tox; extra == "testing"
Requires-Dist: pytest; extra == "testing"
Requires-Dist: pytest-cov; extra == "testing"
Requires-Dist: pytest-qt; extra == "testing"
Requires-Dist: napari; extra == "testing"
Requires-Dist: pyqt5; extra == "testing"
